{
  "chapter": "社会经济",
  "word_count": 171,
  "words": [
    {
      "word": "economy",
      "pos": "n.",
      "meaning": "经济；节约",
      "tips": "【拆分记忆】将'economy'按音节拆分，结合语境反复练习记忆"
    },
    {
      "word": "trade",
      "pos": "n./v.",
      "meaning": "贸易/交换",
      "tips": "【拆分记忆】将'trade'按音节拆分，结合语境反复练习记忆"
    },
    {
      "word": "market",
      "pos": "n.",
      "meaning": "市场；市场需求",
      "tips": "【拆分记忆】将'market'按音节拆分，结合语境反复练习记忆"
    },
    {
      "word": "industry",
      "pos": "n.",
      "meaning": "工业；产业；勤劳",
      "tips": "【拆分记忆】将'industry'按音节拆分，结合语境反复练习记忆"
    },
    {
      "word": "merchant",
      "pos": "n./adj.",
      "meaning": "商人/商业的",
      "tips": "【拆分记忆】将'merchant'按音节拆分，结合语境反复练习记忆"
    },
    {
      "word": "financial",
      "pos": "adj.",
      "meaning": "财政的；金融的",
      "tips": "【后缀记忆】financial - 以al结尾的形容词，表示'与...有关的'"
    },
    {
      "word": "fund",
      "pos": "v./n.",
      "meaning": "资助/基金；资金",
      "tips": "【基础记忆】fund - 常用基础词汇，多次重复加深印象"
    },
    {
      "word": "donate",
      "pos": "v.",
      "meaning": "捐款；捐献",
      "tips": "【后缀记忆】donate - 以ate结尾的动词，表示'使...'"
    },
    {
      "word": "endow",
      "pos": "v.",
      "meaning": "捐赠；赋予",
      "tips": "【拆分记忆】将'endow'按音节拆分，结合语境反复练习记忆"
    },
    {
      "word": "commercial",
      "pos": "adj./n.",
      "meaning": "商业的/商业广告",
      "tips": "【后缀记忆】commercial - 以al结尾的形容词，表示'与...有关的'"
    },
    {
      "word": "advertise",
      "pos": "v.",
      "meaning": "做广告",
      "tips": "【拆分记忆】将'advertise'按音节拆分，结合语境反复练习记忆"
    },
    {
      "word": "slogan",
      "pos": "n.",
      "meaning": "标语；口号",
      "tips": "【拆分记忆】将'slogan'按音节拆分，结合语境反复练习记忆"
    },
    {
      "word": "purchase",
      "pos": "n./v.",
      "meaning": "购买",
      "tips": "【拆分记忆】将'purchase'按音节拆分，结合语境反复练习记忆"
    },
    {
      "word": "lease",
      "pos": "n./v.",
      "meaning": "租约/出租；租用",
      "tips": "【拆分记忆】将'lease'按音节拆分，结合语境反复练习记忆"
    },
    {
      "word": "afford",
      "pos": "v.",
      "meaning": "负担得起；提供；给予",
      "tips": "【拆分记忆】将'afford'按音节拆分，结合语境反复练习记忆"
    },
    {
      "word": "retail",
      "pos": "n./v.",
      "meaning": "零售/以...价格零售",
      "tips": "【拆分记忆】将'retail'按音节拆分，结合语境反复练习记忆"
    },
    {
      "word": "chain",
      "pos": "n.",
      "meaning": "一连串；连锁店",
      "tips": "【拆分记忆】将'chain'按音节拆分，结合语境反复练习记忆"
    },
    {
      "word": "grocery",
      "pos": "n.",
      "meaning": "食品杂货店",
      "tips": "【拆分记忆】将'grocery'按音节拆分，结合语境反复练习记忆"
    },
    {
      "word": "discount",
      "pos": "n./v.",
      "meaning": "折扣/打折出售",
      "tips": "【拆分记忆】将'discount'按音节拆分，结合语境反复练习记忆"
    },
    {
      "word": "promotion",
      "pos": "n.",
      "meaning": "促销活动；晋升",
      "tips": "【后缀记忆】promotion - 以tion结尾的名词，表示动作或状态"
    },
    {
      "word": "voucher",
      "pos": "n.",
      "meaning": "代金券",
      "tips": "【拆分记忆】将'voucher'按音节拆分，结合语境反复练习记忆"
    },
    {
      "word": "coupon",
      "pos": "n.",
      "meaning": "优惠券",
      "tips": "【拆分记忆】将'coupon'按音节拆分，结合语境反复练习记忆"
    },
    {
      "word": "currency",
      "pos": "n.",
      "meaning": "货币；通用，流行",
      "tips": "【拆分记忆】将'currency'按音节拆分，结合语境反复练习记忆"
    },
    {
      "word": "exchange",
      "pos": "n.",
      "meaning": "交换；兑换",
      "tips": "【拆分记忆】将'exchange'按音节拆分，结合语境反复练习记忆"
    },
    {
      "word": "swap/swop",
      "pos": "v./n.",
      "meaning": "交换",
      "tips": "【拆分记忆】将'swap/swop'按音节拆分，结合语境反复练习记忆"
    },
    {
      "word": "receipt",
      "pos": "n.",
      "meaning": "收据；收到",
      "tips": "【拆分记忆】将'receipt'按音节拆分，结合语境反复练习记忆"
    },
    {
      "word": "invoice",
      "pos": "n./v.",
      "meaning": "发票/开发票给",
      "tips": "【拆分记忆】将'invoice'按音节拆分，结合语境反复练习记忆"
    },
    {
      "word": "tax",
      "pos": "n./v.",
      "meaning": "税/对...征税",
      "tips": "【基础记忆】tax - 常用基础词汇，多次重复加深印象"
    },
    {
      "word": "levy",
      "pos": "n./v.",
      "meaning": "税款/征收",
      "tips": "【基础记忆】levy - 常用基础词汇，多次重复加深印象"
    },
    {
      "word": "tariff",
      "pos": "n.",
      "meaning": "关税；（公共服务的）收费",
      "tips": "【拆分记忆】将'tariff'按音节拆分，结合语境反复练习记忆"
    },
    {
      "word": "duty",
      "pos": "n.",
      "meaning": "职责；义务；关税",
      "tips": "【基础记忆】duty - 常用基础词汇，多次重复加深印象"
    },
    {
      "word": "impose",
      "pos": "v.",
      "meaning": "强加；征收（书款）",
      "tips": "【拆分记忆】将'impose'按音节拆分，结合语境反复练习记忆"
    },
    {
      "word": "consume",
      "pos": "v.",
      "meaning": "消耗，吃，喝",
      "tips": "【拆分记忆】将'consume'按音节拆分，结合语境反复练习记忆"
    },
    {
      "word": "spend",
      "pos": "v./n.",
      "meaning": "花费/开支",
      "tips": "【拆分记忆】将'spend'按音节拆分，结合语境反复练习记忆"
    },
    {
      "word": "cost",
      "pos": "v./n.",
      "meaning": "需付费/费用；代价；成本",
      "tips": "【基础记忆】cost - 常用基础词汇，多次重复加深印象"
    },
    {
      "word": "expense",
      "pos": "n.",
      "meaning": "费用；花费",
      "tips": "【拆分记忆】将'expense'按音节拆分，结合语境反复练习记忆"
    },
    {
      "word": "revenue",
      "pos": "n.",
      "meaning": "（公司、组织的）收入；（政府的）税收",
      "tips": "【拆分记忆】将'revenue'按音节拆分，结合语境反复练习记忆"
    },
    {
      "word": "gross",
      "pos": "adj.",
      "meaning": "总的；毛的",
      "tips": "【拆分记忆】将'gross'按音节拆分，结合语境反复练习记忆"
    },
    {
      "word": "recession",
      "pos": "n.",
      "meaning": "经济衰退",
      "tips": "【拆分记忆】将'recession'按音节拆分，结合语境反复练习记忆"
    },
    {
      "word": "depression",
      "pos": "n.",
      "meaning": "沮丧；消沉；萧条期；不景气",
      "tips": "【拆分记忆】将'depression'按音节拆分，结合语境反复练习记忆"
    },
    {
      "word": "crisis",
      "pos": "n.",
      "meaning": "危机",
      "tips": "【拆分记忆】将'crisis'按音节拆分，结合语境反复练习记忆"
    },
    {
      "word": "security",
      "pos": "n.",
      "meaning": "安全工作；安全；[securities]证券",
      "tips": "【拆分记忆】将'security'按音节拆分，结合语境反复练习记忆"
    },
    {
      "word": "bond",
      "pos": "n.",
      "meaning": "债券",
      "tips": "【基础记忆】bond - 常用基础词汇，多次重复加深印象"
    },
    {
      "word": "debt",
      "pos": "n.",
      "meaning": "债务",
      "tips": "【基础记忆】debt - 常用基础词汇，多次重复加深印象"
    },
    {
      "word": "deficit",
      "pos": "n.",
      "meaning": "赤字；逆差",
      "tips": "【拆分记忆】将'deficit'按音节拆分，结合语境反复练习记忆"
    },
    {
      "word": "inflation",
      "pos": "n.",
      "meaning": "通货膨胀",
      "tips": "【后缀记忆】inflation - 以tion结尾的名词，表示动作或状态"
    },
    {
      "word": "deflation",
      "pos": "n.",
      "meaning": "通货紧缩",
      "tips": "【后缀记忆】deflation - 以tion结尾的名词，表示动作或状态"
    },
    {
      "word": "dwindle",
      "pos": "v.",
      "meaning": "缩小；减少",
      "tips": "【拆分记忆】将'dwindle'按音节拆分，结合语境反复练习记忆"
    },
    {
      "word": "decrease",
      "pos": "n./v.",
      "meaning": "减少；减小/（使）减少；（使）减小",
      "tips": "【拆分记忆】将'decrease'按音节拆分，结合语境反复练习记忆"
    },
    {
      "word": "downsize",
      "pos": "v.",
      "meaning": "使精简；裁员",
      "tips": "【拆分记忆】将'downsize'按音节拆分，结合语境反复练习记忆"
    },
    {
      "word": "decline",
      "pos": "v./n.",
      "meaning": "下降",
      "tips": "【拆分记忆】将'decline'按音节拆分，结合语境反复练习记忆"
    },
    {
      "word": "diminish",
      "pos": "v.",
      "meaning": "减少；贬低",
      "tips": "【拆分记忆】将'diminish'按音节拆分，结合语境反复练习记忆"
    },
    {
      "word": "reduce",
      "pos": "v.",
      "meaning": "减少，减小",
      "tips": "【拆分记忆】将'reduce'按音节拆分，结合语境反复练习记忆"
    },
    {
      "word": "increase",
      "pos": "n./v.",
      "meaning": "增加，增长/（使）增加，（使）增长",
      "tips": "【拆分记忆】将'increase'按音节拆分，结合语境反复练习记忆"
    },
    {
      "word": "increment",
      "pos": "n.",
      "meaning": "增加量；定期加薪",
      "tips": "【拆分记忆】将'increment'按音节拆分，结合语境反复练习记忆"
    },
    {
      "word": "growth",
      "pos": "n.",
      "meaning": "增长；生长",
      "tips": "【拆分记忆】将'growth'按音节拆分，结合语境反复练习记忆"
    },
    {
      "word": "escalate",
      "pos": "v.",
      "meaning": "（使）逐步升级；（使）不断恶化",
      "tips": "【后缀记忆】escalate - 以ate结尾的动词，表示'使...'"
    },
    {
      "word": "expand",
      "pos": "v.",
      "meaning": "扩充；扩大；扩展",
      "tips": "【拆分记忆】将'expand'按音节拆分，结合语境反复练习记忆"
    },
    {
      "word": "influx",
      "pos": "n.",
      "meaning": "流入，涌进",
      "example": "|influx of capital 资本的涌进",
      "example_translation": "[需要翻译]",
      "tips": "【拆分记忆】将'influx'按音节拆分，结合语境反复练习记忆"
    },
    {
      "word": "affluent",
      "pos": "adj.",
      "meaning": "富裕的；富足的",
      "tips": "【拆分记忆】将'affluent'按音节拆分，结合语境反复练习记忆"
    },
    {
      "word": "enrich",
      "pos": "v.",
      "meaning": "使富有；充实",
      "tips": "【拆分记忆】将'enrich'按音节拆分，结合语境反复练习记忆"
    },
    {
      "word": "sufficient",
      "pos": "adj.",
      "meaning": "足够的",
      "example": "|insufficient adj. 不足的",
      "example_translation": "[需要翻译]",
      "tips": "【拆分记忆】将'sufficient'按音节拆分，结合语境反复练习记忆"
    },
    {
      "word": "adequate",
      "pos": "adj.",
      "meaning": "足够的；合格的",
      "tips": "【后缀记忆】adequate - 以ate结尾的动词，表示'使...'"
    },
    {
      "word": "spare",
      "pos": "adj./v.",
      "meaning": "多余的；空闲的/剩余",
      "tips": "【拆分记忆】将'spare'按音节拆分，结合语境反复练习记忆"
    },
    {
      "word": "saving",
      "pos": "n.",
      "meaning": "节约；节省",
      "tips": "【后缀记忆】saving - 以ing结尾，表示正在进行或状态"
    },
    {
      "word": "redundant",
      "pos": "adj.",
      "meaning": "多余的；被裁减的",
      "tips": "【拆分记忆】将'redundant'按音节拆分，结合语境反复练习记忆"
    },
    {
      "word": "lack",
      "pos": "n./v.",
      "meaning": "缺乏；不足/缺少；没有",
      "tips": "【基础记忆】lack - 常用基础词汇，多次重复加深印象"
    },
    {
      "word": "company",
      "pos": "n.",
      "meaning": "公司；陪伴；剧团",
      "example": "|keep sb. company 陪伴某人",
      "example_translation": "[需要翻译]",
      "tips": "【拆分记忆】将'company'按音节拆分，结合语境反复练习记忆"
    },
    {
      "word": "firm",
      "pos": "n./adj.",
      "meaning": "公司/坚定的；坚固的",
      "tips": "【基础记忆】firm - 常用基础词汇，多次重复加深印象"
    },
    {
      "word": "enterprise",
      "pos": "n.",
      "meaning": "企业；事业",
      "tips": "【拆分记忆】将'enterprise'按音节拆分，结合语境反复练习记忆"
    },
    {
      "word": "agent",
      "pos": "n.",
      "meaning": "代理人，代理商",
      "tips": "【拆分记忆】将'agent'按音节拆分，结合语境反复练习记忆"
    },
    {
      "word": "entity",
      "pos": "n.",
      "meaning": "实体，独立存在物",
      "tips": "【拆分记忆】将'entity'按音节拆分，结合语境反复练习记忆"
    },
    {
      "word": "invest",
      "pos": "v.",
      "meaning": "投资；投入",
      "tips": "【拆分记忆】将'invest'按音节拆分，结合语境反复练习记忆"
    },
    {
      "word": "input",
      "pos": "n.",
      "meaning": "输入信息；投入物",
      "tips": "【拆分记忆】将'input'按音节拆分，结合语境反复练习记忆"
    },
    {
      "word": "product",
      "pos": "n.",
      "meaning": "产品；产物",
      "tips": "【拆分记忆】将'product'按音节拆分，结合语境反复练习记忆"
    },
    {
      "word": "acquisition",
      "pos": "n.",
      "meaning": "获得；（对公司的）并购",
      "tips": "【后缀记忆】acquisition - 以tion结尾的名词，表示动作或状态"
    },
    {
      "word": "goods",
      "pos": "n.",
      "meaning": "商品；货物",
      "tips": "【拆分记忆】将'goods'按音节拆分，结合语境反复练习记忆"
    },
    {
      "word": "cargo",
      "pos": "n.",
      "meaning": "货物",
      "tips": "【拆分记忆】将'cargo'按音节拆分，结合语境反复练习记忆"
    },
    {
      "word": "insure",
      "pos": "v.",
      "meaning": "确保；给...上保险",
      "tips": "【拆分记忆】将'insure'按音节拆分，结合语境反复练习记忆"
    },
    {
      "word": "guarantee",
      "pos": "v./n.",
      "meaning": "担保；确保/保证；保修单；担保金；担保物",
      "tips": "【拆分记忆】将'guarantee'按音节拆分，结合语境反复练习记忆"
    },
    {
      "word": "reliable",
      "pos": "adj.",
      "meaning": "可靠的，可信赖的",
      "tips": "【拆分记忆】将'reliable'按音节拆分，结合语境反复练习记忆"
    },
    {
      "word": "negotiation",
      "pos": "n.",
      "meaning": "谈判，协商",
      "tips": "【后缀记忆】negotiation - 以tion结尾的名词，表示动作或状态"
    },
    {
      "word": "attend",
      "pos": "v.",
      "meaning": "参加，出席",
      "tips": "【拆分记忆】将'attend'按音节拆分，结合语境反复练习记忆"
    },
    {
      "word": "absent",
      "pos": "adj.",
      "meaning": "缺席的；不在场的；心不在焉的",
      "tips": "【拆分记忆】将'absent'按音节拆分，结合语境反复练习记忆"
    },
    {
      "word": "sale",
      "pos": "n.",
      "meaning": "买；销售；销售额",
      "tips": "【基础记忆】sale - 常用基础词汇，多次重复加深印象"
    },
    {
      "word": "wholesale",
      "pos": "n.",
      "meaning": "批发",
      "tips": "【拆分记忆】将'wholesale'按音节拆分，结合语境反复练习记忆"
    },
    {
      "word": "auction",
      "pos": "v./n.",
      "meaning": "拍卖",
      "tips": "【后缀记忆】auction - 以tion结尾的名词，表示动作或状态"
    },
    {
      "word": "bid",
      "pos": "v./n.",
      "meaning": "出价；投标",
      "tips": "【基础记忆】bid - 常用基础词汇，多次重复加深印象"
    },
    {
      "word": "deal",
      "pos": "v./n.",
      "meaning": "买卖；[~ with]处理；应付/协议；交易；大量",
      "tips": "【基础记忆】deal - 常用基础词汇，多次重复加深印象"
    },
    {
      "word": "transaction",
      "pos": "n.",
      "meaning": "（一笔）交易；业务",
      "tips": "【后缀记忆】transaction - 以tion结尾的名词，表示动作或状态"
    },
    {
      "word": "turnover",
      "pos": "n.",
      "meaning": "（人员的）流动率；营业额",
      "tips": "【拆分记忆】将'turnover'按音节拆分，结合语境反复练习记忆"
    },
    {
      "word": "dump",
      "pos": "v.",
      "meaning": "丢弃；倾倒；倾销",
      "tips": "【基础记忆】dump - 常用基础词汇，多次重复加深印象"
    },
    {
      "word": "export",
      "pos": "v./n.",
      "meaning": "出口/出口；出口商品",
      "tips": "【拆分记忆】将'export'按音节拆分，结合语境反复练习记忆"
    },
    {
      "word": "import",
      "pos": "v./n.",
      "meaning": "进口/进口；进口商品",
      "tips": "【拆分记忆】将'import'按音节拆分，结合语境反复练习记忆"
    },
    {
      "word": "quota",
      "pos": "n.",
      "meaning": "限额；配额；定额",
      "tips": "【拆分记忆】将'quota'按音节拆分，结合语境反复练习记忆"
    },
    {
      "word": "share",
      "pos": "n./v.",
      "meaning": "股份，股票；一份/分享；共享；分担",
      "tips": "【拆分记忆】将'share'按音节拆分，结合语境反复练习记忆"
    },
    {
      "word": "benefit",
      "pos": "n./v.",
      "meaning": "益处/有利于；获益",
      "tips": "【拆分记忆】将'benefit'按音节拆分，结合语境反复练习记忆"
    },
    {
      "word": "interest",
      "pos": "n./v.",
      "meaning": "兴趣；利益；利息/使感兴趣",
      "tips": "【拆分记忆】将'interest'按音节拆分，结合语境反复练习记忆"
    },
    {
      "word": "dividend",
      "pos": "n.",
      "meaning": "股息；红利",
      "tips": "【拆分记忆】将'dividend'按音节拆分，结合语境反复练习记忆"
    },
    {
      "word": "stock",
      "pos": "n.",
      "meaning": "股本；股票；库存",
      "tips": "【拆分记忆】将'stock'按音节拆分，结合语境反复练习记忆"
    },
    {
      "word": "account",
      "pos": "n.",
      "meaning": "账户；解释",
      "tips": "【拆分记忆】将'account'按音节拆分，结合语境反复练习记忆"
    },
    {
      "word": "deposit",
      "pos": "n.",
      "meaning": "存款；押金",
      "tips": "【拆分记忆】将'deposit'按音节拆分，结合语境反复练习记忆"
    },
    {
      "word": "instalment/installment",
      "pos": "n.",
      "meaning": "（分期付款的）一期付款",
      "tips": "【拆分记忆】将'instalment/installment'按音节拆分，结合语境反复练习记忆"
    },
    {
      "word": "cheque/check",
      "pos": "n.",
      "meaning": "支票",
      "tips": "【拆分记忆】将'cheque/check'按音节拆分，结合语境反复练习记忆"
    },
    {
      "word": "cash",
      "pos": "n./v.",
      "meaning": "现金/兑现（支票）",
      "tips": "【基础记忆】cash - 常用基础词汇，多次重复加深印象"
    },
    {
      "word": "coin",
      "pos": "n./v.",
      "meaning": "硬币/铸币；创造（新词语）",
      "tips": "【基础记忆】coin - 常用基础词汇，多次重复加深印象"
    },
    {
      "word": "shilling",
      "pos": "n.",
      "meaning": "先令",
      "tips": "【后缀记忆】shilling - 以ing结尾，表示正在进行或状态"
    },
    {
      "word": "copper",
      "pos": "n.",
      "meaning": "铜；[~s]铜币；警察",
      "example": "|cop n. 警察",
      "example_translation": "[需要翻译]",
      "tips": "【拆分记忆】将'copper'按音节拆分，结合语境反复练习记忆"
    },
    {
      "word": "treasure",
      "pos": "n.",
      "meaning": "金银财宝；宝物；珍品",
      "tips": "【拆分记忆】将'treasure'按音节拆分，结合语境反复练习记忆"
    },
    {
      "word": "wealth",
      "pos": "n.",
      "meaning": "财富；丰富",
      "tips": "【拆分记忆】将'wealth'按音节拆分，结合语境反复练习记忆"
    },
    {
      "word": "estate",
      "pos": "n.",
      "meaning": "地产；遗产",
      "tips": "【后缀记忆】estate - 以ate结尾的动词，表示'使...'"
    },
    {
      "word": "possess",
      "pos": "v.",
      "meaning": "占用；拥有；影响；控制",
      "tips": "【拆分记忆】将'possess'按音节拆分，结合语境反复练习记忆"
    },
    {
      "word": "legacy",
      "pos": "n.",
      "meaning": "遗赠；遗产",
      "tips": "【拆分记忆】将'legacy'按音节拆分，结合语境反复练习记忆"
    },
    {
      "word": "descend",
      "pos": "v.",
      "meaning": "下降，下来",
      "tips": "【拆分记忆】将'descend'按音节拆分，结合语境反复练习记忆"
    },
    {
      "word": "worthy",
      "pos": "adj.",
      "meaning": "有价值的",
      "tips": "【拆分记忆】将'worthy'按音节拆分，结合语境反复练习记忆"
    },
    {
      "word": "valuable",
      "pos": "adj.",
      "meaning": "很值钱的；贵重的；很重要的",
      "tips": "【拆分记忆】将'valuable'按音节拆分，结合语境反复练习记忆"
    },
    {
      "word": "cheap",
      "pos": "adj.",
      "meaning": "廉价的；质劣价低的",
      "tips": "【拆分记忆】将'cheap'按音节拆分，结合语境反复练习记忆"
    },
    {
      "word": "incentive",
      "pos": "n.",
      "meaning": "刺激；激励",
      "tips": "【拆分记忆】将'incentive'按音节拆分，结合语境反复练习记忆"
    },
    {
      "word": "accelerate",
      "pos": "v.",
      "meaning": "加速",
      "tips": "【后缀记忆】accelerate - 以ate结尾的动词，表示'使...'"
    },
    {
      "word": "prompt",
      "pos": "v./adj.",
      "meaning": "促使/迅速的",
      "tips": "【拆分记忆】将'prompt'按音节拆分，结合语境反复练习记忆"
    },
    {
      "word": "salary",
      "pos": "n.",
      "meaning": "工资；（按月领的）薪水",
      "tips": "【拆分记忆】将'salary'按音节拆分，结合语境反复练习记忆"
    },
    {
      "word": "income",
      "pos": "n.",
      "meaning": "收入",
      "tips": "【拆分记忆】将'income'按音节拆分，结合语境反复练习记忆"
    },
    {
      "word": "wage",
      "pos": "n.",
      "meaning": "（通常指按周领的）工钱",
      "tips": "【基础记忆】wage - 常用基础词汇，多次重复加深印象"
    },
    {
      "word": "payment",
      "pos": "n.",
      "meaning": "支付；支付的款项；付款额",
      "tips": "【拆分记忆】将'payment'按音节拆分，结合语境反复练习记忆"
    },
    {
      "word": "refund",
      "pos": "n./v.",
      "meaning": "退款",
      "tips": "【拆分记忆】将'refund'按音节拆分，结合语境反复练习记忆"
    },
    {
      "word": "reimburse",
      "pos": "v.",
      "meaning": "赔偿；补偿",
      "tips": "【拆分记忆】将'reimburse'按音节拆分，结合语境反复练习记忆"
    },
    {
      "word": "payroll",
      "pos": "n.",
      "meaning": "工资名单",
      "tips": "【拆分记忆】将'payroll'按音节拆分，结合语境反复练习记忆"
    },
    {
      "word": "remuneration",
      "pos": "n.",
      "meaning": "报酬",
      "tips": "【后缀记忆】remuneration - 以tion结尾的名词，表示动作或状态"
    },
    {
      "word": "subsidy",
      "pos": "n.",
      "meaning": "津贴，补贴",
      "example": "|subsidise=subsidize v. 资助，给...发津贴",
      "example_translation": "[需要翻译]",
      "tips": "【拆分记忆】将'subsidy'按音节拆分，结合语境反复练习记忆"
    },
    {
      "word": "earn",
      "pos": "v.",
      "meaning": "赚得；赢得；获得",
      "tips": "【基础记忆】earn - 常用基础词汇，多次重复加深印象"
    },
    {
      "word": "undertaking",
      "pos": "n.",
      "meaning": "任务；事业；许诺；保证",
      "example": "I give an undertaking that we shall proceed with the legislation|a written undertaking 书面保证。an undertaking clause 承诺条款",
      "example_translation": "[需要翻译]",
      "tips": "【后缀记忆】undertaking - 以ing结尾，表示正在进行或状态"
    },
    {
      "word": "career",
      "pos": "n.",
      "meaning": "职业；事业；职业生涯",
      "tips": "【拆分记忆】将'career'按音节拆分，结合语境反复练习记忆"
    },
    {
      "word": "profession",
      "pos": "n.",
      "meaning": "职业",
      "tips": "【拆分记忆】将'profession'按音节拆分，结合语境反复练习记忆"
    },
    {
      "word": "occupation",
      "pos": "n.",
      "meaning": "占领，占据；职业",
      "tips": "【后缀记忆】occupation - 以tion结尾的名词，表示动作或状态"
    },
    {
      "word": "job",
      "pos": "n.",
      "meaning": "职业；工作",
      "tips": "【基础记忆】job - 常用基础词汇，多次重复加深印象"
    },
    {
      "word": "vocation",
      "pos": "n.",
      "meaning": "（认为特别适合自己的）职业；使命感",
      "tips": "【后缀记忆】vocation - 以tion结尾的名词，表示动作或状态"
    },
    {
      "word": "labour/labor",
      "pos": "n.",
      "meaning": "劳动；体力劳动",
      "tips": "【拆分记忆】将'labour/labor'按音节拆分，结合语境反复练习记忆"
    },
    {
      "word": "workforce",
      "pos": "n.",
      "meaning": "劳动力；全体员工",
      "tips": "【拆分记忆】将'workforce'按音节拆分，结合语境反复练习记忆"
    },
    {
      "word": "workaholic",
      "pos": "n.",
      "meaning": "工作狂",
      "tips": "【拆分记忆】将'workaholic'按音节拆分，结合语境反复练习记忆"
    },
    {
      "word": "personnel",
      "pos": "n.",
      "meaning": "人员，职员；人事部门",
      "tips": "【拆分记忆】将'personnel'按音节拆分，结合语境反复练习记忆"
    },
    {
      "word": "clerk",
      "pos": "n.",
      "meaning": "店员，办事员，接待员",
      "tips": "【拆分记忆】将'clerk'按音节拆分，结合语境反复练习记忆"
    },
    {
      "word": "interview",
      "pos": "n./v.",
      "meaning": "面试；采访/对...进行面试；采访",
      "tips": "【拆分记忆】将'interview'按音节拆分，结合语境反复练习记忆"
    },
    {
      "word": "résumé/resume",
      "pos": "n.",
      "meaning": "UK /ˈrez.juː.meɪ/ US /ˈrez.ə.meɪ/ 履历；简历；摘要",
      "tips": "【拆分记忆】将'résumé/resume'按音节拆分，结合语境反复练习记忆"
    },
    {
      "word": "recommend",
      "pos": "v.",
      "meaning": "推荐；劝告；介绍",
      "tips": "【拆分记忆】将'recommend'按音节拆分，结合语境反复练习记忆"
    },
    {
      "word": "employ",
      "pos": "v.",
      "meaning": "雇用；采用",
      "tips": "【拆分记忆】将'employ'按音节拆分，结合语境反复练习记忆"
    },
    {
      "word": "hire",
      "pos": "v./n.",
      "meaning": "雇用；租用/租赁（业）",
      "tips": "【基础记忆】hire - 常用基础词汇，多次重复加深印象"
    },
    {
      "word": "fire",
      "pos": "v./n.",
      "meaning": "解雇/火",
      "tips": "【基础记忆】fire - 常用基础词汇，多次重复加深印象"
    },
    {
      "word": "lay-off",
      "pos": "n.",
      "meaning": "（因岗位不足的）解雇；裁员；歇工期",
      "tips": "【拆分记忆】将'lay-off'按音节拆分，结合语境反复练习记忆"
    },
    {
      "word": "dismiss",
      "pos": "v.",
      "meaning": "解雇；解散；驳回",
      "tips": "【拆分记忆】将'dismiss'按音节拆分，结合语境反复练习记忆"
    },
    {
      "word": "discharge",
      "pos": "v./n.",
      "meaning": "解雇/卸货",
      "tips": "【拆分记忆】将'discharge'按音节拆分，结合语境反复练习记忆"
    },
    {
      "word": "resign",
      "pos": "v.",
      "meaning": "辞去；辞职",
      "tips": "【拆分记忆】将'resign'按音节拆分，结合语境反复练习记忆"
    },
    {
      "word": "sack",
      "pos": "n./v.",
      "meaning": "大口袋，麻布袋/开除",
      "tips": "【基础记忆】sack - 常用基础词汇，多次重复加深印象"
    },
    {
      "word": "retire",
      "pos": "v.",
      "meaning": "退休",
      "tips": "【拆分记忆】将'retire'按音节拆分，结合语境反复练习记忆"
    },
    {
      "word": "result",
      "pos": "n./v.",
      "meaning": "结果，后果/导致",
      "tips": "【拆分记忆】将'result'按音节拆分，结合语境反复练习记忆"
    },
    {
      "word": "failure",
      "pos": "n.",
      "meaning": "失败；失败的人；失败的事",
      "tips": "【拆分记忆】将'failure'按音节拆分，结合语境反复练习记忆"
    },
    {
      "word": "abortion",
      "pos": "n.",
      "meaning": "人工流产；中途失败",
      "tips": "【后缀记忆】abortion - 以tion结尾的名词，表示动作或状态"
    },
    {
      "word": "loss",
      "pos": "n.",
      "meaning": "遗失；损失；亏损",
      "tips": "【基础记忆】loss - 常用基础词汇，多次重复加深印象"
    },
    {
      "word": "opportunity",
      "pos": "n.",
      "meaning": "机会；时机",
      "tips": "【拆分记忆】将'opportunity'按音节拆分，结合语境反复练习记忆"
    },
    {
      "word": "chance",
      "pos": "n.",
      "meaning": "机会；可能性",
      "tips": "【拆分记忆】将'chance'按音节拆分，结合语境反复练习记忆"
    },
    {
      "word": "choose",
      "pos": "v.",
      "meaning": "选择",
      "tips": "【拆分记忆】将'choose'按音节拆分，结合语境反复练习记忆"
    },
    {
      "word": "change",
      "pos": "n.",
      "meaning": "改变",
      "tips": "【拆分记忆】将'change'按音节拆分，结合语境反复练习记忆"
    },
    {
      "word": "solve",
      "pos": "v.",
      "meaning": "解答，解决",
      "tips": "【拆分记忆】将'solve'按音节拆分，结合语境反复练习记忆"
    },
    {
      "word": "develop",
      "pos": "v.",
      "meaning": "发展，开发",
      "tips": "【拆分记忆】将'develop'按音节拆分，结合语境反复练习记忆"
    },
    {
      "word": "sustainable",
      "pos": "adj.",
      "meaning": "可持续的",
      "tips": "【拆分记忆】将'sustainable'按音节拆分，结合语境反复练习记忆"
    },
    {
      "word": "improve",
      "pos": "v.",
      "meaning": "改善；改进",
      "tips": "【拆分记忆】将'improve'按音节拆分，结合语境反复练习记忆"
    },
    {
      "word": "manage",
      "pos": "v.",
      "meaning": "管理；设法做到",
      "tips": "【拆分记忆】将'manage'按音节拆分，结合语境反复练习记忆"
    },
    {
      "word": "regulate",
      "pos": "v.",
      "meaning": "管理；调整",
      "tips": "【后缀记忆】regulate - 以ate结尾的动词，表示'使...'"
    },
    {
      "word": "sanction",
      "pos": "n./v.",
      "meaning": "批准；制裁/批准；对...制裁",
      "tips": "【后缀记忆】sanction - 以tion结尾的名词，表示动作或状态"
    },
    {
      "word": "coordinate",
      "pos": "v./n.",
      "meaning": "调和；协调/坐标",
      "tips": "【后缀记忆】coordinate - 以ate结尾的动词，表示'使...'"
    },
    {
      "word": "cooperate",
      "pos": "v.",
      "meaning": "合作；协作",
      "tips": "【后缀记忆】cooperate - 以ate结尾的动词，表示'使...'"
    },
    {
      "word": "collaborate",
      "pos": "v.",
      "meaning": "合作",
      "tips": "【后缀记忆】collaborate - 以ate结尾的动词，表示'使...'"
    }
  ]
}